protein_data_handler/__init__.py
protein_data_handler/alignment.py
protein_data_handler/config.yaml
protein_data_handler/fasta.py
protein_data_handler/helpers/__init__.py
protein_data_handler/helpers/config/__init__.py
protein_data_handler/helpers/config/yaml.py
protein_data_handler/helpers/database/__init__.py
protein_data_handler/helpers/database/database.py
protein_data_handler/helpers/parser/__init__.py
protein_data_handler/helpers/parser/parser.py
protein_data_handler/models/__init__.py
protein_data_handler/models/uniprot.py
protein_data_handler/pdb.py
protein_data_handler/uniprot.py
protein_data_handler-1.0.9.dist-info/METADATA
protein_data_handler-1.0.9.dist-info/WHEEL
protein_data_handler-1.0.9.dist-info/RECORD
