Metadata-Version: 2.1
Name: protein-data-handler
Version: 1.0.9
Summary: Comprehensive Python Module for Protein Data Management: Designed for streamlined integration and processing of protein information from both UniProt and PDB. Equipped with features for concurrent data fetching, robust error handling, and database synchronization.
Author: frapercan
Author-email: frapercan1@alum.us.es
Requires-Python: >=3.10,<4.0
Classifier: Programming Language :: Python :: 3
Classifier: Programming Language :: Python :: 3.10
Classifier: Programming Language :: Python :: 3.11
Requires-Dist: bio (>=1.6.0,<2.0.0)
Requires-Dist: biopython (>=1.81,<2.0)
Requires-Dist: docopt (>=0.6.2,<0.7.0)
Requires-Dist: psycopg2 (>=2.9.9,<3.0.0)
Requires-Dist: py-cdhit (>=0.8.0,<0.9.0)
Requires-Dist: pyyaml (>=6.0.1,<7.0.0)
Requires-Dist: sqlalchemy (>=2.0.23,<3.0.0)
